{"ZjqVJWs0qXwdgdE8YwTeEw==":"background17.jpeg","PHmX9W1QET14zUIWsYaa0A==":"img-589.jpeg","6dYB4ISv9JaFpMraTanmVw==":"img-549.jpeg","ldPYnbBnY7HFQBbCM5LgGg==":"img-327.jpeg","MHzxSJM2U9IUxLEQ9aDYxA==":"img-1858.jpeg","iZl2pNCNM9cpsa5I3KOFFQ==":"img-1746.jpeg","TztI9iNyDtGtrmpnC9kuIQ==":"img-795.jpeg","pBLOJ2gkl4fuNyywgyMfLw==":"img-636.jpeg","Fovx8bzHfmxuzrpAFP1S9Q==":"img-510.jpeg","09ESpOH845CFS33kisJUoA==":"img-511.jpeg","temAKx8OAFbCSJ5PyFvbwQ==":"img-512.jpeg","8RNLGnzW5hekDrFAQvM7+w==":"img-584.jpeg","Eqgmuuvdvem9V4b29wJMRw==":"img-443.jpeg"}